<?xml version="1.0" ?>
<annotation>
	<folder>imgs/</folder>
	<filename>Inria_337.jpg</filename>
	<path>Inria_337.jpg</path>
	<size>
		<width>623</width>
		<height>532</height>
		<depth>3</depth>
	</size>
	<segmented>0</segmented>
	<object>
		<name>hand</name>
		<pose>Unspecified</pose>
		<truncated>0</truncated>
		<difficult>0</difficult>
		<bndbox>
			<xmin>313</xmin>
			<ymin>251</ymin>
			<xmax>338</xmax>
			<ymax>268</ymax>
		</bndbox>
	</object>
	<object>
		<name>hand</name>
		<pose>Unspecified</pose>
		<truncated>0</truncated>
		<difficult>0</difficult>
		<bndbox>
			<xmin>325</xmin>
			<ymin>211</ymin>
			<xmax>345</xmax>
			<ymax>218</ymax>
		</bndbox>
	</object>
</annotation>
