<?xml version="1.0" ?>
<annotation>
	<folder>imgs/</folder>
	<filename>Inria_192.jpg</filename>
	<path>Inria_192.jpg</path>
	<size>
		<width>522</width>
		<height>592</height>
		<depth>3</depth>
	</size>
	<segmented>0</segmented>
	<object>
		<name>hand</name>
		<pose>Unspecified</pose>
		<truncated>0</truncated>
		<difficult>0</difficult>
		<bndbox>
			<xmin>256</xmin>
			<ymin>214</ymin>
			<xmax>273</xmax>
			<ymax>236</ymax>
		</bndbox>
	</object>
	<object>
		<name>hand</name>
		<pose>Unspecified</pose>
		<truncated>0</truncated>
		<difficult>0</difficult>
		<bndbox>
			<xmin>304</xmin>
			<ymin>297</ymin>
			<xmax>320</xmax>
			<ymax>309</ymax>
		</bndbox>
	</object>
</annotation>
