<?xml version="1.0" ?>
<annotation>
	<folder>imgs/</folder>
	<filename>Inria_37.jpg</filename>
	<path>Inria_37.jpg</path>
	<size>
		<width>258</width>
		<height>255</height>
		<depth>3</depth>
	</size>
	<segmented>0</segmented>
	<object>
		<name>hand</name>
		<pose>Unspecified</pose>
		<truncated>0</truncated>
		<difficult>0</difficult>
		<bndbox>
			<xmin>190</xmin>
			<ymin>227</ymin>
			<xmax>205</xmax>
			<ymax>239</ymax>
		</bndbox>
	</object>
	<object>
		<name>hand</name>
		<pose>Unspecified</pose>
		<truncated>0</truncated>
		<difficult>0</difficult>
		<bndbox>
			<xmin>126</xmin>
			<ymin>127</ymin>
			<xmax>136</xmax>
			<ymax>138</ymax>
		</bndbox>
	</object>
</annotation>
