<?xml version="1.0" ?>
<annotation>
	<folder>imgs/</folder>
	<filename>Inria_496.jpg</filename>
	<path>Inria_496.jpg</path>
	<size>
		<width>480</width>
		<height>640</height>
		<depth>3</depth>
	</size>
	<segmented>0</segmented>
	<object>
		<name>hand</name>
		<pose>Unspecified</pose>
		<truncated>0</truncated>
		<difficult>0</difficult>
		<bndbox>
			<xmin>226</xmin>
			<ymin>403</ymin>
			<xmax>254</xmax>
			<ymax>429</ymax>
		</bndbox>
	</object>
	<object>
		<name>hand</name>
		<pose>Unspecified</pose>
		<truncated>0</truncated>
		<difficult>0</difficult>
		<bndbox>
			<xmin>226</xmin>
			<ymin>403</ymin>
			<xmax>254</xmax>
			<ymax>429</ymax>
		</bndbox>
	</object>
	<object>
		<name>hand</name>
		<pose>Unspecified</pose>
		<truncated>0</truncated>
		<difficult>0</difficult>
		<bndbox>
			<xmin>231</xmin>
			<ymin>316</ymin>
			<xmax>263</xmax>
			<ymax>345</ymax>
		</bndbox>
	</object>
</annotation>
