<?xml version="1.0" ?>
<annotation>
	<folder>imgs/</folder>
	<filename>Inria_491.jpg</filename>
	<path>Inria_491.jpg</path>
	<size>
		<width>976</width>
		<height>735</height>
		<depth>3</depth>
	</size>
	<segmented>0</segmented>
	<object>
		<name>hand</name>
		<pose>Unspecified</pose>
		<truncated>0</truncated>
		<difficult>0</difficult>
		<bndbox>
			<xmin>565</xmin>
			<ymin>526</ymin>
			<xmax>645</xmax>
			<ymax>577</ymax>
		</bndbox>
	</object>
	<object>
		<name>hand</name>
		<pose>Unspecified</pose>
		<truncated>0</truncated>
		<difficult>0</difficult>
		<bndbox>
			<xmin>471</xmin>
			<ymin>299</ymin>
			<xmax>541</xmax>
			<ymax>352</ymax>
		</bndbox>
	</object>
	<object>
		<name>hand</name>
		<pose>Unspecified</pose>
		<truncated>0</truncated>
		<difficult>0</difficult>
		<bndbox>
			<xmin>227</xmin>
			<ymin>441</ymin>
			<xmax>284</xmax>
			<ymax>490</ymax>
		</bndbox>
	</object>
	<object>
		<name>hand</name>
		<pose>Unspecified</pose>
		<truncated>0</truncated>
		<difficult>0</difficult>
		<bndbox>
			<xmin>398</xmin>
			<ymin>201</ymin>
			<xmax>426</xmax>
			<ymax>223</ymax>
		</bndbox>
	</object>
	<object>
		<name>hand</name>
		<pose>Unspecified</pose>
		<truncated>0</truncated>
		<difficult>0</difficult>
		<bndbox>
			<xmin>483</xmin>
			<ymin>96</ymin>
			<xmax>544</xmax>
			<ymax>134</ymax>
		</bndbox>
	</object>
	<object>
		<name>hand</name>
		<pose>Unspecified</pose>
		<truncated>0</truncated>
		<difficult>0</difficult>
		<bndbox>
			<xmin>395</xmin>
			<ymin>1</ymin>
			<xmax>429</xmax>
			<ymax>23</ymax>
		</bndbox>
	</object>
</annotation>
