<?xml version="1.0" ?>
<annotation>
	<folder>imgs/</folder>
	<filename>Poselet_324.jpg</filename>
	<path>Poselet_324.jpg</path>
	<size>
		<width>640</width>
		<height>479</height>
		<depth>3</depth>
	</size>
	<segmented>0</segmented>
	<object>
		<name>hand</name>
		<pose>Unspecified</pose>
		<truncated>0</truncated>
		<difficult>0</difficult>
		<bndbox>
			<xmin>343</xmin>
			<ymin>346</ymin>
			<xmax>406</xmax>
			<ymax>371</ymax>
		</bndbox>
	</object>
	<object>
		<name>hand</name>
		<pose>Unspecified</pose>
		<truncated>0</truncated>
		<difficult>0</difficult>
		<bndbox>
			<xmin>475</xmin>
			<ymin>426</ymin>
			<xmax>501</xmax>
			<ymax>442</ymax>
		</bndbox>
	</object>
	<object>
		<name>hand</name>
		<pose>Unspecified</pose>
		<truncated>0</truncated>
		<difficult>0</difficult>
		<bndbox>
			<xmin>268</xmin>
			<ymin>207</ymin>
			<xmax>289</xmax>
			<ymax>225</ymax>
		</bndbox>
	</object>
	<object>
		<name>hand</name>
		<pose>Unspecified</pose>
		<truncated>0</truncated>
		<difficult>0</difficult>
		<bndbox>
			<xmin>214</xmin>
			<ymin>125</ymin>
			<xmax>235</xmax>
			<ymax>145</ymax>
		</bndbox>
	</object>
	<object>
		<name>hand</name>
		<pose>Unspecified</pose>
		<truncated>0</truncated>
		<difficult>0</difficult>
		<bndbox>
			<xmin>276</xmin>
			<ymin>176</ymin>
			<xmax>297</xmax>
			<ymax>196</ymax>
		</bndbox>
	</object>
	<object>
		<name>hand</name>
		<pose>Unspecified</pose>
		<truncated>0</truncated>
		<difficult>0</difficult>
		<bndbox>
			<xmin>183</xmin>
			<ymin>177</ymin>
			<xmax>203</xmax>
			<ymax>198</ymax>
		</bndbox>
	</object>
</annotation>
