<?xml version="1.0" ?>
<annotation>
	<folder>imgs/</folder>
	<filename>VOC2010_561.jpg</filename>
	<path>VOC2010_561.jpg</path>
	<size>
		<width>500</width>
		<height>201</height>
		<depth>3</depth>
	</size>
	<segmented>0</segmented>
	<object>
		<name>hand</name>
		<pose>Unspecified</pose>
		<truncated>0</truncated>
		<difficult>0</difficult>
		<bndbox>
			<xmin>207</xmin>
			<ymin>141</ymin>
			<xmax>246</xmax>
			<ymax>172</ymax>
		</bndbox>
	</object>
	<object>
		<name>hand</name>
		<pose>Unspecified</pose>
		<truncated>0</truncated>
		<difficult>0</difficult>
		<bndbox>
			<xmin>221</xmin>
			<ymin>22</ymin>
			<xmax>264</xmax>
			<ymax>40</ymax>
		</bndbox>
	</object>
</annotation>
